{
    "patientsData": [
        {
            "id": 1,
            "mrn": "MRN-111-1111",
            "name": "Edward",
            "dob": "1950-03-25",
            "schedule": "2017-03-25T12:00:00Z",
            "gender": "male",
            "mhistory": [
                "Condition 1",
                "Condition 2",
                "Condition 3",
                "Condition 4"
            ]
        },
        {
            "id": 2,
            "mrn": "MRN-222-2222",
            "name": "Steve",
            "dob": "1955-06-05",
            "schedule": "2017-01-29T12:00:00Z",
            "gender": "male",
            "mhistory": [
                "Condition 1",
                "Condition 2",
                "Condition 3"
            ]
        },
        {
            "id": 3,
            "mrn": "MRN-333-3333",
            "name": "Ana",
            "dob": "1960-01-22",
            "schedule": "2017-02-09T12:00:00Z",
            "gender": "female",
            "mhistory": [
                "Condition 1",
                "Condition 2"
            ]
        },
        {
            "id": 4,
            "mrn": "MRN-444-4444",
            "name": "Olivia",
            "dob": "1965-10-12",
            "schedule": "2017-03-11T12:00:00Z",
            "gender": "female",
            "mhistory": [
                "Condition 1",
                "Condition 2"
            ]
        },
        {
            "id": 5,
            "mrn": "MRN-555-5555",
            "name": "Peter",
            "dob": "1970-10-12",
            "schedule": "2017-04-19T12:00:00Z",
            "gender": "male",
            "mhistory": [
                "Condition 1",
                "Condition 2",
                "Condition 3",
                "Condition 4",
                "Condition 5",
                "Condition 6"
            ]
        },
        {
            "id": 6,
            "mrn": "MRN-666-6666",
            "name": "Jane",
            "dob": "1975-12-12",
            "schedule": "2017-04-15T12:00:00Z",
            "gender": "female",
            "mhistory": [
                "Condition 1",
                "Condition 2",
                "Condition 3"
            ]
        },
        {
            "id": 7,
            "mrn": "MRN-777-7777",
            "name": "Sam",
            "dob": "1980-11-09",
            "schedule": "2017-04-18T12:00:00Z",
            "gender": "male",
            "mhistory": [
                "Condition 1",
                "Condition 2"
            ]
        },
        {
            "id": 8,
            "mrn": "MRN-888-8888",
            "name": "Deborah",
            "dob": "1985-06-09",
            "schedule": "2017-05-01T12:00:00Z",
            "gender": "female",
            "mhistory": [
                "Condition 1",
                "Condition 2"
            ]
        },
        {
            "id": 9,
            "mrn": "MRN-999-9999",
            "name": "Albert",
            "dob": "1990-06-09",
            "schedule": "2017-05-03T12:00:00Z",
            "gender": "male",
            "mhistory": [
                "Condition 1"
            ]
        },
        {
            "id": 9,
            "mrn": "MRN-101-0101",
            "name": "Vanessa",
            "dob": "1995-05-05",
            "schedule": "2017-05-05T12:00:00Z",
            "gender": "female",
            "mhistory": []
        }
    ]
}